simple_namespace/__init__.py
simple_namespace/main.py
simple_namespace-1.0.0.dist-info/METADATA
simple_namespace-1.0.0.dist-info/WHEEL
simple_namespace-1.0.0.dist-info/top_level.txt
simple_namespace-1.0.0.dist-info/RECORD
