Metadata-Version: 2.1
Name: simple-namespace
Version: 1.0.0
Summary: Organize code better with namespaces
Home-page: https://github.com/jeff-hykin/simple_namespace
Author: Jeff Hykin
Author-email: jeff.hykin@gmail.com
License: MIT
Platform: UNKNOWN
Classifier: Development Status :: 5 - Production/Stable
Classifier: Intended Audience :: Developers
Classifier: Programming Language :: Python
Classifier: Programming Language :: Python :: 3
Classifier: Operating System :: OS Independent
Requires-Python: >=3.6
